AUTHORS
LICENSE
MANIFEST.in
README.rst
pyproject.toml
setup.py
copt/__init__.py
copt/constraint.py
copt/datasets.py
copt/frank_wolfe.py
copt/loss.py
copt/penalty.py
copt/proximal_gradient.py
copt/randomized.py
copt/splitting.py
copt/tv_prox.py
copt/utils.py
copt/utils_pytorch.py
copt.egg-info/PKG-INFO
copt.egg-info/SOURCES.txt
copt.egg-info/dependency_links.txt
copt.egg-info/requires.txt
copt.egg-info/top_level.txt
copt/data/img1.csv
doc/Makefile
doc/citing.rst
doc/conf.py
doc/index.rst
doc/logo.png
doc/loss_functions.rst
doc/make.bat
doc/solvers.rst
doc/utils.rst
doc/_static/css/custom.css
doc/auto_examples/index.rst.new
doc/auto_examples/plot_accelerated.ipynb
doc/auto_examples/plot_accelerated.py
doc/auto_examples/plot_accelerated.py.md5
doc/auto_examples/plot_accelerated.rst
doc/auto_examples/plot_accelerated_codeobj.pickle
doc/auto_examples/plot_group_lasso.ipynb
doc/auto_examples/plot_group_lasso.py
doc/auto_examples/plot_group_lasso.py.md5
doc/auto_examples/plot_group_lasso.rst
doc/auto_examples/plot_group_lasso_codeobj.pickle
doc/auto_examples/plot_jax_copt.ipynb
doc/auto_examples/plot_jax_copt.py
doc/auto_examples/plot_jax_copt.py.md5
doc/auto_examples/plot_jax_copt.rst
doc/auto_examples/plot_jax_copt_codeobj.pickle
doc/auto_examples/plot_saga_vs_svrg.ipynb
doc/auto_examples/plot_saga_vs_svrg.py
doc/auto_examples/plot_saga_vs_svrg.py.md5
doc/auto_examples/plot_saga_vs_svrg.rst
doc/auto_examples/plot_saga_vs_svrg_codeobj.pickle
doc/auto_examples/sg_execution_times.rst
doc/auto_examples/frank_wolfe/plot_sfw_real_data.py
doc/auto_examples/frank_wolfe/plot_sparse_benchmark.ipynb
doc/auto_examples/frank_wolfe/plot_sparse_benchmark.py
doc/auto_examples/frank_wolfe/plot_sparse_benchmark.py.md5
doc/auto_examples/frank_wolfe/plot_sparse_benchmark.rst
doc/auto_examples/frank_wolfe/plot_sparse_benchmark_codeobj.pickle
doc/auto_examples/frank_wolfe/plot_sparse_benchmark_pairwise.ipynb
doc/auto_examples/frank_wolfe/plot_sparse_benchmark_pairwise.py
doc/auto_examples/frank_wolfe/plot_sparse_benchmark_pairwise.py.md5
doc/auto_examples/frank_wolfe/plot_sparse_benchmark_pairwise.rst
