Metadata-Version: 2.1
Name: copt
Version: 0.9.2
Summary: Library for composite optimization in Python
Home-page: http://pypi.python.org/pypi/copt
Author: Fabian Pedregosa
Author-email: f@bianp.net
License: New BSD License
Classifier: Development Status :: 5 - Production/Stable
Classifier: Intended Audience :: Science/Research
Classifier: Intended Audience :: Developers
Classifier: License :: OSI Approved
Classifier: Programming Language :: Python
Classifier: Programming Language :: Python :: 2
Classifier: Programming Language :: Python :: 3
Classifier: Topic :: Software Development
Classifier: Operating System :: POSIX
Classifier: Operating System :: Unix
License-File: LICENSE
License-File: AUTHORS
Requires-Dist: numpy
Requires-Dist: scipy
Requires-Dist: tqdm
Requires-Dist: scikit-learn
Requires-Dist: six
